nitec/__init__.py
nitec/classifier.py
nitec/model.py
nitec/results.py
nitec/utils.py
nitec/visualize.py
nitec-0.0.2.dist-info/LICENSE.md
nitec-0.0.2.dist-info/METADATA
nitec-0.0.2.dist-info/WHEEL
nitec-0.0.2.dist-info/top_level.txt
nitec-0.0.2.dist-info/RECORD
