Metadata-Version: 2.1
Name: nitec
Version: 0.0.2
Summary: The official PyTorch implementation of NITEC for eye contact detection.
Author: Thorsten Hempel, Magnus Jung, Ahmed Abdelrahman
Project-URL: homepath, https://github.com/thohemp/nitec
Project-URL: repository, https://github.com/thohemp/nitec
Keywords: eye contact,estimation,human-robot interact,hri,deep-learning,pytorch,engagement,wacv
Classifier: Programming Language :: Python :: 3
Requires-Python: >3.8
License-File: LICENSE.md
Requires-Dist: wheel
Requires-Dist: numpy >=1.19.5
Requires-Dist: opencv-python >=4.8.0.74
Requires-Dist: pandas >=2.0.3
Requires-Dist: Pillow >=8.4.0
Requires-Dist: torch >=2.0.1
Requires-Dist: torchvision >=0.15.2
